openbb_tiingo/__init__.py
openbb_tiingo/models/__init__.py
openbb_tiingo/models/company_news.py
openbb_tiingo/models/crypto_historical.py
openbb_tiingo/models/currency_historical.py
openbb_tiingo/models/equity_historical.py
openbb_tiingo/models/trailing_dividend_yield.py
openbb_tiingo/models/world_news.py
openbb_tiingo/utils/__init__.py
openbb_tiingo/utils/helpers.py
openbb_tiingo-1.4.1.dist-info/METADATA
openbb_tiingo-1.4.1.dist-info/WHEEL
openbb_tiingo-1.4.1.dist-info/entry_points.txt
openbb_tiingo-1.4.1.dist-info/RECORD
